Workbook
Name Excel_BuiltIn__FilterDatabase: Hoja2_2!$A$1:$R$110

Sheet Hoja2_2
A1: N.º | B1: Cédula | C1: Apellido(s) | D1: Nombre (s) | E1: Escuela(s) | F1: N° de Personal | G1: Fecha Aniversaria | H1: Años Servicio | I1: Correspondiente al Periodo vacacional: | J1: Desde | K1: Hasta | L1: Total Días | M1: Correspondiente al Periodo (s) vacacional: | N1: Indicador | O1: Teléfono | P1: Supervisor Inmed. / Indicador /Tlf | Q1: Cédula | R1: Cargo Actual
A2: 1 | B2: 19603449 | C2: ACOSTA | D2: PATRICIA | E2: UE LIBERTADOR BOLÍVAR | F2: 2247672 | G2: 43473 | H2: 7 | I2: 2026 | J2: 46235 | K2: 46280 | L2: 46 | M2: 2026 | N2: ACOSTAPH | O2: 0426-7200383 | P2: LUIS ALFREDO VELÁSQUEZ ALCÁZAR | Q2: 17242954 | R2: ESPECIALISTA EN DIFICULTADES DE APRENDIZ
A3: 2 | B3: 18463516 | C3: AGUILERA | D3: VIRGINIA | E3: UE LIBERTADOR BOLÍVAR | F3: 2247620 | G3: 44214 | H3: 5 | I3: 2026 | J3: 46235 | K3: 46280 | L3: 46 | M3: 2026 | N3: AGUILERAVS | O3: 0424-9202587 | P3: LUIS ALFREDO VELÁSQUEZ ALCÁZAR | Q3: 17242954 | R3: DOCENTE MEDIA GENERAL
A4: 3 | B4: 18172869 | C4: ALBORNOZ | D4: ISABEL | E4: UE LIBERTADOR BOLÍVAR | F4: 2247630 | G4: 43473 | H4: 7 | I4: 2026 | J4: 46235 | K4: 46280 | L4: 46 | M4: 2026 | N4: ALBORNOZIH | O4: 0426-3981776 | P4: LUIS ALFREDO VELÁSQUEZ ALCÁZAR | Q4: 17242954 | R4: DOCENTE EDUCACIÓN INICIAL
A5: 4 | B5: 13092755 | C5: BARRETO | D5: KARINA | E5: UE LIBERTADOR BOLÍVAR | F5: 2078111 | G5: 38302 | H5: 21 | I5: 2026 | J5: 46235 | K5: 46280 | L5: 46 | M5: 2026 | N5: BARRETOKD | O5: 0416-1948996 | P5: LUIS ALFREDO VELÁSQUEZ ALCÁZAR | Q5: 17242954 | R5: DOCENTE MEDIA GENERAL
A6: 5 | B6: 18274289 | C6: BEJAS | D6: SULMARY | E6: UE LIBERTADOR BOLÍVAR | F6: 2247628 | G6: 43473 | H6: 7 | I6: 2026 | J6: 46235 | K6: 46280 | L6: 46 | M6: 2026 | N6: BEJASS | O6: 0424-9329569 | P6: LUIS ALFREDO VELÁSQUEZ ALCÁZAR | Q6: 17242954 | R6: DOCENTE MEDIA GENERAL
A7: 6 | B7: 22718748 | C7: BERMUDEZ GONZALEZ | D7: FRANCHESCA G | E7: UE LIBERTADOR BOLÍVAR | F7: 8065643 | G7: 44942 | H7: 3 | I7: 2026 | J7: 46235 | K7: 46280 | L7: 46 | M7: 2026 | O7: 0424-9651651 | P7: LUIS ALFREDO VELÁSQUEZ ALCÁZAR | Q7: 17242954 | R7: DOCENTE PRIMARIA
A8: 7 | B8: 16722294 | C8: BRITO | D8: JESLHOR | E8: UE LIBERTADOR BOLÍVAR | F8: 2205978 | G8: 41624 | H8: 12 | I8: 2026 | J8: 46235 | K8: 46280 | L8: 46 | M8: 2026 | N8: BRITOJKX | O8: 0412-9487630 | P8: LUIS ALFREDO VELÁSQUEZ ALCÁZAR | Q8: 17242954 | R8: DOCENTE PRIMARIA
A9: 8 | B9: 14859067 | C9: CANELON | D9: JUAN | E9: UE LIBERTADOR BOLÍVAR | F9: 2247674 | G9: 43473 | H9: 7 | I9: 2026 | J9: 46235 | K9: 46280 | L9: 46 | M9: 2026 | N9: CANELONJN | O9: 0424-4238157 | P9: LUIS ALFREDO VELÁSQUEZ ALCÁZAR | Q9: 17242954 | R9: DOCENTE MEDIA GENERAL
A10: 9 | B10: 17483709 | C10: CELIZ | D10: LORIANIS | E10: UE LIBERTADOR BOLÍVAR | F10: 2177721 | G10: 41222 | H10: 13 | I10: 2026 | J10: 46235 | K10: 46280 | L10: 46 | M10: 2026 | N10: CELIZL | O10: 0412-9494450 | P10: LUIS ALFREDO VELÁSQUEZ ALCÁZAR | Q10: 17242954 | R10: DOCENTE MEDIA GENERAL
A11: 10 | B11: 19080636 | C11: DIAZ MOLINA | D11: MOLINA CAROLINA | E11: UE LIBERTADOR BOLÍVAR | F11: 2209335 | G11: 41753 | H11: 12 | I11: 2026 | J11: 46235 | K11: 46280 | L11: 46 | M11: 2026 | N11: DIAZPCX | O11: 0416-9900981 | P11: LUIS ALFREDO VELÁSQUEZ ALCÁZAR | Q11: 17242954 | R11: PSICOPEDAGOGO
A12: 11 | B12: 16807474 | C12: DURAN | D12: TRINELLYS | E12: UE LIBERTADOR BOLÍVAR | F12: 2137991 | G12: 39904 | H12: 17 | I12: 2026 | J12: 46235 | K12: 46280 | L12: 46 | M12: 2026 | N12: DURAMTN | O12: 0424-9188018 | P12: LUIS ALFREDO VELÁSQUEZ ALCÁZAR | Q12: 17242954 | R12: DOCENTE PRIMARIA
A13: 12 | B13: 15335432 | C13: FIGUEROA G. | D13: TEOBALDO | E13: UE LIBERTADOR BOLÍVAR | F13: 2079830 | G13: 38412 | H13: 21 | I13: 2026 | J13: 46235 | K13: 46280 | L13: 46 | M13: 2026 | N13: FIGUEROAT | O13: 0416-6976328 | P13: LUIS ALFREDO VELÁSQUEZ ALCÁZAR | Q13: 17242954 | R13: SUDIRECTOR ADMINISTRATIVO
A14: 13 | B14: 19038253 | C14: FUENMAYOR LIPORACHI | D14: ISLENY ADR | E14: UE LIBERTADOR BOLÍVAR | F14: 2209264 | G14: 41754 | H14: 12 | I14: 2026 | J14: 46235 | K14: 46280 | L14: 46 | M14: 2026 | N14: FUENMAYORIS | O14: 0424-9091817 | P14: LUIS ALFREDO VELÁSQUEZ ALCÁZAR | Q14: 17242954 | R14: DOCENTE MEDIA GENERAL
A15: 14 | B15: 12067865 | C15: GARCIA ARENAS | D15: NEIDA | E15: UE LIBERTADOR BOLÍVAR | F15: 2206179 | G15: 41628 | H15: 12 | I15: 2026 | J15: 46235 | K15: 46280 | L15: 46 | M15: 2026 | N15: GARCIANML | O15: 0414-9989327 | P15: LUIS ALFREDO VELÁSQUEZ ALCÁZAR | Q15: 17242954 | R15: DOCENTE PRIMARIA
A16: 15 | B16: 17933097 | C16: GARCIA LAREZ | D16: YENIRE | E16: UE LIBERTADOR BOLÍVAR | F16: 2247631 | G16: 43473 | H16: 7 | I16: 2026 | J16: 46235 | K16: 46280 | L16: 46 | M16: 2026 | N16: GARCIAYTH | O16: 0416-7860704 | P16: LUIS ALFREDO VELÁSQUEZ ALCÁZAR | Q16: 17242954 | R16: DOCENTE EDUCACIÓN INICIAL
A17: 16 | B17: 14367610 | C17: GONZALEZ | D17: ANA | E17: UE LIBERTADOR BOLÍVAR | F17: 2090264 | G17: 38631 | H17: 20 | I17: 2026 | J17: 46235 | K17: 46280 | L17: 46 | M17: 2026 | N17: GONZALEZAEG | O17: 0424-9464834 | P17: LUIS ALFREDO VELÁSQUEZ ALCÁZAR | Q17: 17242954 | R17: COORDINADOR DE EVALUACIÓN
A18: 17 | B18: 17546584 | C18: GONZALEZ | D18: ELIANA LIZKEIRA | E18: UE LIBERTADOR BOLÍVAR | F18: 2177712 | G18: 41008 | H18: 14 | I18: 2026 | J18: 46235 | K18: 46280 | L18: 46 | M18: 2026 | N18: GONZALEZEKB | O18: 0412-1275548 | P18: LUIS ALFREDO VELÁSQUEZ ALCÁZAR | Q18: 17242954 | R18: DOCENTE MEDIA GENERAL
A19: 18 | B19: 18788707 | C19: GONZALEZ | D19: YASIVIT | E19: UE LIBERTADOR BOLÍVAR | F19: 2177808 | G19: 41008 | H19: 14 | I19: 2026 | J19: 46235 | K19: 46280 | L19: 46 | M19: 2026 | N19: GONZALEZYDT | O19: 0416-9062003 | P19: LUIS ALFREDO VELÁSQUEZ ALCÁZAR | Q19: 17242954 | R19: SUDIRECTOR ACADÉMICO
A20: 19 | B20: 20001991 | C20: GONZALEZ BARCELO | D20: JUAN | E20: UE LIBERTADOR BOLÍVAR | F20: 2247622 | G20: 44596 | H20: 4 | I20: 2026 | J20: 46235 | K20: 46280 | L20: 46 | M20: 2026 | N20: GONZALEZJA | O20: 0424-9288814 | P20: LUIS ALFREDO VELÁSQUEZ ALCÁZAR | Q20: 17242954 | R20: DOCENTE PRIMARIA
A21: 20 | B21: 22720162 | C21: GONZALEZ TREJO | D21: NOHELY SORIBEL | E21: UE LIBERTADOR BOLÍVAR | F21: 8065646 | G21: 44942 | H21: 3 | I21: 2026 | J21: 46235 | K21: 46280 | L21: 46 | M21: 2026 | O21: 0414-8637262 | P21: LUIS ALFREDO VELÁSQUEZ ALCÁZAR | Q21: 17242954 | R21: DOCENTE MEDIA GENERAL
A22: 21 | B22: 19079220 | C22: GONZALEZ VARGAS | D22: BETZAIDA ZARAY | E22: UE LIBERTADOR BOLÍVAR | F22: 8044828 | G22: 43707 | H22: 6 | I22: 2026 | J22: 46235 | K22: 46280 | L22: 46 | M22: 2026 | N22: GONZALEZBZX | O22: 0416-9824842 | P22: LUIS ALFREDO VELÁSQUEZ ALCÁZAR | Q22: 17242954 | R22: DOCENTE MEDIA GENERAL
A23: 22 | B23: 18075785 | C23: GONZALEZ YANEZ | D23: EYLLING KEYROVI | E23: UE LIBERTADOR BOLÍVAR | F23: 8065641 | G23: 44942 | H23: 3 | I23: 2026 | J23: 46235 | K23: 46280 | L23: 46 | M23: 2026 | O23: 0412-2406062 | P23: LUIS ALFREDO VELÁSQUEZ ALCÁZAR | Q23: 17242954 | R23: DOCENTE PRIMARIA
A24: 23 | B24: 12891949 | C24: HERNANDEZ | D24: DENYSSE JOSEFINA | E24: UE LIBERTADOR BOLÍVAR | F24: 4007923 | G24: 38621 | H24: 20 | I24: 2026 | J24: 46235 | K24: 46280 | L24: 46 | M24: 2026 | N24: HERNADEZDJY | O24: 0424-5725526 | P24: LUIS ALFREDO VELÁSQUEZ ALCÁZAR | Q24: 17242954 | R24: DEFENSOR ESCOLAR
A25: 24 | B25: 16374774 | C25: HURTADO | D25: ELINOR DEL VALLE | E25: UE LIBERTADOR BOLÍVAR | F25: 2209248 | G25: 41754 | H25: 12 | I25: 2026 | J25: 46235 | K25: 46280 | L25: 46 | M25: 2026 | N25: HURTADOEQ | O25: 0412-3340579 | P25: LUIS ALFREDO VELÁSQUEZ ALCÁZAR | Q25: 17242954 | R25: DOCENTE MEDIA GENERAL
A26: 25 | B26: 19080588 | C26: JIMENEZ ANGULO | D26: JOSE ALY | E26: UE LIBERTADOR BOLÍVAR | F26: 8065654 | G26: 44942 | H26: 3 | I26: 2026 | J26: 46235 | K26: 46280 | L26: 46 | M26: 2026 | O26: 0412-8783907 | P26: LUIS ALFREDO VELÁSQUEZ ALCÁZAR | Q26: 17242954 | R26: DOCENTE MEDIA GENERAL
A27: 26 | B27: 17722878 | C27: JIMENEZ MATA | D27: JAMNYMAR JOSE | E27: UE LIBERTADOR BOLÍVAR | F27: 2162520 | G27: 40470 | H27: 15 | I27: 2026 | J27: 46235 | K27: 46280 | L27: 46 | M27: 2026 | N27: JIMENEZJJQ | O27: 0414-7686402 | P27: LUIS ALFREDO VELÁSQUEZ ALCÁZAR | Q27: 17242954 | R27: DOCENTE EDUCACIÓN INICIAL
A28: 27 | B28: 17723779 | C28: JIMENEZ NUNEZ | D28: LUISA | E28: UE LIBERTADOR BOLÍVAR | F28: 2247675 | G28: 43473 | H28: 7 | I28: 2026 | J28: 46235 | K28: 46280 | L28: 46 | M28: 2026 | N28: JIMENEZLAW | O28: 0414-7701960 | P28: LUIS ALFREDO VELÁSQUEZ ALCÁZAR | Q28: 17242954 | R28: ESPECIALISTA EN DIFICULTADES DE APRENDIZ
A29: 28 | B29: 16375125 | C29: LEON | D29: EIRA A | E29: UE LIBERTADOR BOLÍVAR | F29: 2137952 | G29: 39904 | H29: 17 | I29: 2026 | J29: 46235 | K29: 46280 | L29: 46 | M29: 2026 | N29: LEONEAY | O29: 0414-9918333 | P29: LUIS ALFREDO VELÁSQUEZ ALCÁZAR | Q29: 17242954 | R29: DOCENTE MEDIA GENERAL
A30: 29 | B30: 16699098 | C30: LOPEZ | D30: FERNANDA | E30: UE LIBERTADOR BOLÍVAR | F30: 2247624 | G30: 43473 | H30: 7 | I30: 2026 | J30: 46235 | K30: 46280 | L30: 46 | M30: 2026 | N30: LOPEZFAF | O30: 0424-9554985 | P30: LUIS ALFREDO VELÁSQUEZ ALCÁZAR | Q30: 17242954 | R30: DOCENTE PRIMARIA
A31: 30 | B31: 18080019 | C31: LOPEZ TORRES | D31: NELLYS JOSEFINA | E31: UE LIBERTADOR BOLÍVAR | F31: 8065638 | G31: 44942 | H31: 3 | I31: 2026 | J31: 46235 | K31: 46280 | L31: 46 | M31: 2026 | O31: 0412-8655197 | P31: LUIS ALFREDO VELÁSQUEZ ALCÁZAR | Q31: 17242954 | R31: DOCENTE PRIMARIA
A32: 31 | B32: 14703619 | C32: LUCAS | D32: JOSE | E32: UE LIBERTADOR BOLÍVAR | F32: 2177720 | G32: 41008 | H32: 14 | I32: 2026 | J32: 46235 | K32: 46280 | L32: 46 | M32: 2026 | N32: LUCASJN | O32: 0416-7926910 | P32: LUIS ALFREDO VELÁSQUEZ ALCÁZAR | Q32: 17242954 | R32: DOCENTE MEDIA GENERAL
A33: 32 | B33: 17090701 | C33: MAITA | D33: YARITZA G | E33: UE LIBERTADOR BOLÍVAR | F33: 2138245 | G33: 39925 | H33: 17 | I33: 2026 | J33: 46235 | K33: 46280 | L33: 46 | M33: 2026 | N33: MAITAYG | O33: 0412-0913435 | P33: LUIS ALFREDO VELÁSQUEZ ALCÁZAR | Q33: 17242954 | R33: DOCENTE MEDIA GENERAL
A34: 33 | B34: 15631248 | C34: MARCANO | D34: YUDERCY | E34: UE LIBERTADOR BOLÍVAR | F34: 2247671 | G34: 43473 | H34: 7 | I34: 2026 | J34: 46235 | K34: 46280 | L34: 46 | M34: 2026 | N34: MARCANOYAX | O34: 0426-0355870 | P34: LUIS ALFREDO VELÁSQUEZ ALCÁZAR | Q34: 17242954 | R34: PSICOPEDAGOGO
A35: 34 | B35: 17241569 | C35: MARCANO MARTIN | D35: EDUARDO | E35: UE LIBERTADOR BOLÍVAR | F35: 2209352 | G35: 41754 | H35: 12 | I35: 2026 | J35: 46235 | K35: 46280 | L35: 46 | M35: 2026 | N35: MARCANOMEH | O35: 0412-9429171 | P35: LUIS ALFREDO VELÁSQUEZ ALCÁZAR | Q35: 17242954 | R35: DOCENTE MEDIA GENERAL
A36: 35 | B36: 14531830 | C36: MARTIN | D36: MINERVA | E36: UE LIBERTADOR BOLÍVAR | F36: 2247617 | G36: 43108 | H36: 8 | I36: 2026 | J36: 46235 | K36: 46280 | L36: 46 | M36: 2026 | N36: MARTINMJ | O36: 0416-1818890 | P36: LUIS ALFREDO VELÁSQUEZ ALCÁZAR | Q36: 17242954 | R36: DOCENTE EDUCACIÓN INICIAL
A37: 36 | B37: 14622890 | C37: MARTINEZ | D37: ALBERTO | E37: UE LIBERTADOR BOLÍVAR | F37: 2247619 | G37: 43473 | H37: 7 | I37: 2026 | J37: 46235 | K37: 46280 | L37: 46 | M37: 2026 | N37: MARTINEZARE | O37: 0426-4941095 | P37: LUIS ALFREDO VELÁSQUEZ ALCÁZAR | Q37: 17242954 | R37: DOCENTE MEDIA GENERAL
A38: 37 | B38: 17113644 | C38: MARTINEZ | D38: MILAGROS | E38: UE LIBERTADOR BOLÍVAR | F38: 2094299 | G38: 16/12/2013 | H38: 12 | I38: 2026 | J38: 46235 | K38: 46268 | L38: 34 | M38: 2026 | N38: MARTINEZMDA | O38: 0412-2980380 | P38: LUIS ALFREDO VELÁSQUEZ ALCÁZAR | Q38: 17242954 | R38: ANALISTA DE ARCHIVO
A39: 38 | B39: 17463095 | C39: MARTINEZ | D39: MARIA | E39: UE LIBERTADOR BOLÍVAR | F39: 2247634 | G39: 43473 | H39: 7 | I39: 2026 | J39: 46235 | K39: 46280 | L39: 46 | M39: 2026 | N39: MARTINEZMTN | O39: 0416-2889081 | P39: LUIS ALFREDO VELÁSQUEZ ALCÁZAR | Q39: 17242954 | R39: DOCENTE PRIMARIA
A40: 39 | B40: 20310911 | C40: MARTÍNEZ CABRERA | D40: MARÍA ALEJANDRA | E40: UE LIBERTADOR BOLÍVAR | F40: 8065634 | G40: 44942 | H40: 3 | I40: 2026 | J40: 46235 | K40: 46280 | L40: 46 | M40: 2026 | O40: 0424-9559942 | P40: LUIS ALFREDO VELÁSQUEZ ALCÁZAR | Q40: 17242954 | R40: DOCENTE PRIMARIA
A41: 40 | B41: 13656273 | C41: MILLAN | D41: LAURYS DEL VALLE | E41: UE LIBERTADOR BOLÍVAR | F41: 2121182 | G41: 39461 | H41: 18 | I41: 2026 | J41: 46235 | K41: 46280 | L41: 46 | M41: 2026 | N41: MILLANLH | O41: 0416-5893543 | P41: LUIS ALFREDO VELÁSQUEZ ALCÁZAR | Q41: 17242954 | R41: DOCENTE EDUCACIÓN INICIAL
A42: 41 | B42: 17780095 | C42: MILLAN MONTANO | D42: JOSE VICENTE | E42: UE LIBERTADOR BOLÍVAR | F42: 2184717 | G42: 41127 | H42: 13 | I42: 2026 | J42: 46235 | K42: 46280 | L42: 46 | M42: 2026 | N42: MILLANJVX | O42: 0416-1873879 | P42: LUIS ALFREDO VELÁSQUEZ ALCÁZAR | Q42: 17242954 | R42: DIRECTOR ESCUELA LIBERTADOR BOLÍVAR
A43: 42 | B43: 13814605 | C43: MORENO | D43: RUTHMARY | E43: UE LIBERTADOR BOLÍVAR | F43: 2142816 | G43: 39993 | H43: 16 | I43: 2026 | J43: 46235 | K43: 46280 | L43: 46 | M43: 2026 | N43: MORENORJD | O43: 0414-1921643 | P43: LUIS ALFREDO VELÁSQUEZ ALCÁZAR | Q43: 17242954 | R43: DOCENTE MEDIA GENERAL
A44: 43 | B44: 14101477 | C44: NORIEGA | D44: MARYFRANCI | E44: UE LIBERTADOR BOLÍVAR | F44: 2079835 | G44: 38412 | H44: 21 | I44: 2026 | J44: 46235 | K44: 46280 | L44: 46 | M44: 2026 | N44: NORIEGAMS | O44: 0424-9170859 | P44: LUIS ALFREDO VELÁSQUEZ ALCÁZAR | Q44: 17242954 | R44: COORDINADOR DE EVALUACIÓN
A45: 44 | B45: 13915005 | C45: NUCCI | D45: BEATRIZ JOSEFINA | E45: UE LIBERTADOR BOLÍVAR | F45: 4005267 | G45: 37907 | H45: 22 | I45: 2026 | J45: 46235 | K45: 46280 | L45: 46 | M45: 2026 | N45: NUCCIBJ | O45: 0414-8862811 | P45: LUIS ALFREDO VELÁSQUEZ ALCÁZAR | Q45: 17242954 | R45: DOCENTE MEDIA GENERAL
A46: 45 | B46: 11830987 | C46: PARRA SALAZAR | D46: OLGA | E46: UE LIBERTADOR BOLÍVAR | F46: 2053406 | G46: 37151 | H46: 24 | I46: 2026 | J46: 46235 | K46: 46280 | L46: 46 | M46: 2026 | N46: PARRAOD | O46: 0416-2985387 | P46: LUIS ALFREDO VELÁSQUEZ ALCÁZAR | Q46: 17242954 | R46: COORDINADOR PEDAGÓGICO
A47: 46 | B47: 15044802 | C47: PEINADO | D47: YADELSI | E47: UE LIBERTADOR BOLÍVAR | F47: 2247632 | G47: 43473 | H47: 7 | I47: 2026 | J47: 46235 | K47: 46280 | L47: 46 | M47: 2026 | N47: PEINADOY | O47: 0426-2927664 | P47: LUIS ALFREDO VELÁSQUEZ ALCÁZAR | Q47: 17242954 | R47: DOCENTE MEDIA GENERAL
A48: 47 | B48: 22714341 | C48: PERNIA | D48: DANIELA | E48: UE LIBERTADOR BOLÍVAR | F48: 2247676 | G48: 43473 | H48: 7 | I48: 2026 | J48: 46235 | K48: 46280 | L48: 46 | M48: 2026 | N48: PERNIADN | O48: 0426-9634633 | P48: LUIS ALFREDO VELÁSQUEZ ALCÁZAR | Q48: 17242954 | R48: DOCENTE MEDIA GENERAL
A49: 48 | B49: 19079457 | C49: RIVAS | D49: LUIS | E49: UE LIBERTADOR BOLÍVAR | F49: 2247621 | G49: 43473 | H49: 7 | I49: 2026 | J49: 46235 | K49: 46280 | L49: 46 | M49: 2026 | N49: RIVASLJG | O49: 0426-4255537 | P49: LUIS ALFREDO VELÁSQUEZ ALCÁZAR | Q49: 17242954 | R49: DOCENTE MEDIA GENERAL
A50: 49 | B50: 16174810 | C50: RIVAS VILLARROEL | D50: OMAR | E50: UE LIBERTADOR BOLÍVAR | F50: 2247633 | G50: 43837 | H50: 6 | I50: 2026 | J50: 46235 | K50: 46280 | L50: 46 | M50: 2026 | N50: RIVASOX | O50: 0414-8826188 | P50: LUIS ALFREDO VELÁSQUEZ ALCÁZAR | Q50: 17242954 | R50: DOCENTE MEDIA GENERAL
A51: 50 | B51: 9286272 | C51: RODRIGUEZ | D51: CARMEN ELENA | E51: UE LIBERTADOR BOLÍVAR | F51: 2031973 | G51: 34613 | H51: 31 | I51: 2026 | J51: 46235 | K51: 46280 | L51: 46 | M51: 2026 | N51: RODRIGUEZCEU | O51: 0416-7883929 | P51: LUIS ALFREDO VELÁSQUEZ ALCÁZAR | Q51: 17242954 | R51: DOCENTE MEDIA GENERAL
A52: 51 | B52: 18983523 | C52: RODRIGUEZ LOPEZ | D52: ADRIANA MARGARITA | E52: UE LIBERTADOR BOLÍVAR | F52: 8065751 | G52: 44942 | H52: 3 | I52: 2026 | J52: 46235 | K52: 46280 | L52: 46 | M52: 2026 | O52: 0416-3855873 | P52: LUIS ALFREDO VELÁSQUEZ ALCÁZAR | Q52: 17242954 | R52: DOCENTE MEDIA GENERAL
A53: 52 | B53: 22725746 | C53: RONDON GARCIA | D53: YOHANDRI DEL CARMEN | E53: UE LIBERTADOR BOLÍVAR | F53: 8065651 | G53: 44942 | H53: 3 | I53: 2026 | J53: 46235 | K53: 46280 | L53: 46 | M53: 2026 | O53: 0412-1030345 | P53: LUIS ALFREDO VELÁSQUEZ ALCÁZAR | Q53: 17242954 | R53: DOCENTE MEDIA GENERAL
A54: 53 | B54: 17092720 | C54: RONDON VILLARROEL | D54: MARINELLYS | E54: UE LIBERTADOR BOLÍVAR | F54: 2118795 | G54: 39387 | H54: 18 | I54: 2026 | J54: 46235 | K54: 46280 | L54: 46 | M54: 2026 | N54: RONDONMAO | O54: 0426-1871200 | P54: LUIS ALFREDO VELÁSQUEZ ALCÁZAR | Q54: 17242954 | R54: DOCENTE PRIMARIA
A55: 54 | B55: 18174495 | C55: RUIZ | D55: ROMINA DEL VALLE | E55: UE LIBERTADOR BOLÍVAR | F55: 8065628 | G55: 44942 | H55: 3 | I55: 2026 | J55: 46235 | K55: 46280 | L55: 46 | M55: 2026 | O55: 0426-1942900 | P55: LUIS ALFREDO VELÁSQUEZ ALCÁZAR | Q55: 17242954 | R55: DOCENTE EDUCACIÓN INICIAL
A56: 55 | B56: 19875121 | C56: RUIZ VILLARROEL | D56: JULIA ISABEL | E56: UE LIBERTADOR BOLÍVAR | F56: 2209453 | G56: 41754 | H56: 12 | I56: 2026 | J56: 46235 | K56: 46280 | L56: 46 | M56: 2026 | N56: RUIZJIX | O56: 0416-9939770 | P56: LUIS ALFREDO VELÁSQUEZ ALCÁZAR | Q56: 17242954 | R56: DOCENTE MEDIA GENERAL
A57: 56 | B57: 16397151 | C57: SALAZAR | D57: FERNANDO DANIEL | E57: UE LIBERTADOR BOLÍVAR | F57: 2184716 | G57: 41127 | H57: 13 | I57: 2026 | J57: 46235 | K57: 46280 | L57: 46 | M57: 2026 | N57: SALAZARFAD | O57: 0412-8614364 | P57: LUIS ALFREDO VELÁSQUEZ ALCÁZAR | Q57: 17242954 | R57: DOCENTE MEDIA GENERAL
A58: 57 | B58: 11381867 | C58: SALMERON PRESILLA | D58: LUIS RICARDO | E58: UE LIBERTADOR BOLÍVAR | F58: 2094299 | G58: 38784 | H58: 20 | I58: 2026 | J58: 46235 | K58: 46268 | L58: 34 | M58: 2026 | N58: SALMERONLR | O58: 0412-8625780 | P58: LUIS ALFREDO VELÁSQUEZ ALCÁZAR | Q58: 17242954 | R58: ANALISTA MAYOR PROG NAC DE APRENDIZAJE
A59: 58 | B59: 19415615 | C59: URRIETA | D59: ALEXANDER VANESSA | E59: UE LIBERTADOR BOLÍVAR | F59: 2247670 | G59: 43473 | H59: 7 | I59: 2026 | J59: 46235 | K59: 46280 | L59: 46 | M59: 2026 | N59: URRIETAV | O59: 0416-9660315 | P59: LUIS ALFREDO VELÁSQUEZ ALCÁZAR | Q59: 17242954 | R59: DOCENTE MEDIA GENERAL
A60: 59 | B60: 17242954 | C60: VELASQUEZ ALCAZAR | D60: LUIS | E60: UE LIBERTADOR BOLÍVAR | F60: 2124625 | G60: 07/04/2008 | H60: 18 | I60: 2026 | J60: 46235 | K60: 46268 | L60: 34 | M60: 2026 | N60: VELASQUEZLAU | O60: 0424-9107303 | P60: ILIADA CAZORLA | Q60: 16939125 | R60: LIDER ESCUELAS
A61: 60 | B61: 14110180 | C61: ZAMBRANO | D61: JUAN | E61: UE LIBERTADOR BOLÍVAR | F61: 2177723 | G61: 41008 | H61: 14 | I61: 2026 | J61: 46235 | K61: 46280 | L61: 46 | M61: 2026 | N61: ZAMBRANOJEU | O61: 0424-9717566 | P61: LUIS ALFREDO VELÁSQUEZ ALCÁZAR | Q61: 17242954 | R61: COORDINADOR DE CULTURA
A62: 61 | B62: 16396448 | C62: ACOSTA ALFONZO | D62: GABRIELA MARIA | E62: UE SANTA BÁRBARA | F62: 8044815 | G62: 30/08/2019 | H62: 6 | I62: 2026 | J62: 46235 | K62: 46280 | L62: 46 | M62: 2026 | N62: ACOSTAGY | O62: 0412-4989390 | P62: LUIS ALFREDO VELÁSQUEZ ALCÁZAR | Q62: 17242954 | R62: DOCENTE MEDIA GENERAL
A63: 62 | B63: 11842683 | C63: ARCHILES | D63: EULIMAR | E63: UE SANTA BÁRBARA | F63: 2138239 | G63: 22/04/2009 | H63: 17 | I63: 2026 | J63: 46235 | K63: 46280 | L63: 46 | M63: 2026 | N63: ARCHILESE | O63: 0414-7702978 | P63: LUIS ALFREDO VELÁSQUEZ ALCÁZAR | Q63: 17242954 | R63: DOCENTE PRIMARIA
A64: 63 | B64: 12362435 | C64: ARCHILES | D64: SOIRY MAR | E64: UE SANTA BÁRBARA | F64: 8044792 | G64: 30/08/2019 | H64: 6 | I64: 2026 | J64: 46235 | K64: 46280 | L64: 46 | M64: 2026 | N64: ARCHILESS | O64: 0414-8725996 | P64: LUIS ALFREDO VELÁSQUEZ ALCÁZAR | Q64: 17242954 | R64: COORDINADOR DE EVALUACIÓN
A65: 64 | B65: 18983704 | C65: ASTUDILLO ACOSTA | D65: MARIA ANTONEL | E65: UE SANTA BÁRBARA | F65: 8044826 | G65: 30/08/2019 | H65: 6 | I65: 2026 | J65: 46235 | K65: 46280 | L65: 46 | M65: 2026 | N65: ASTUDILLOMA | O65: 0414-3856272 | P65: LUIS ALFREDO VELÁSQUEZ ALCÁZAR | Q65: 17242954 | R65: PSICOPEDAGOGO
A66: 65 | B66: 15510687 | C66: BERMUDEZ HERNANDEZ | D66: JULIO RAFAEL | E66: UE SANTA BÁRBARA | F66: 2129791 | G66: 19/08/2008 | H66: 17 | I66: 2026 | J66: 46235 | K66: 46280 | L66: 46 | M66: 2026 | N66: BERMUDEZJAR | O66: 0414-8576342 | P66: LUIS ALFREDO VELÁSQUEZ ALCÁZAR | Q66: 17242954 | R66: DOCENTE PRIMARIA
A67: 66 | B67: 21499609 | C67: BETANCOURT ESPIN | D67: ANICRIS DEL CARMEN | E67: UE SANTA BÁRBARA | F67: 8050006 | G67: 44008 | H67: 5 | I67: 2026 | J67: 46235 | K67: 46280 | L67: 46 | M67: 2026 | O67: 0424-9383282 | P67: LUIS ALFREDO VELÁSQUEZ ALCÁZAR | Q67: 17242954 | R67: DOCENTE MEDIA GENERAL
A68: 67 | B68: 14192913 | C68: BOLIVAR FIGUEREDO | D68: MILAGROS A | E68: UE SANTA BÁRBARA | F68: 8044825 | G68: 43707 | H68: 6 | I68: 2026 | J68: 46235 | K68: 46280 | L68: 46 | M68: 2026 | O68: 0414-8532210 | P68: LUIS ALFREDO VELÁSQUEZ ALCÁZAR | Q68: 17242954 | R68: ESPECIALISTA EN DIFICULTADES APRENDIZAJE
A69: 68 | B69: 17487413 | C69: BRITO | D69: MARIANNY JOSE | E69: UE SANTA BÁRBARA | F69: 2184715 | G69: 06/08/2012 | H69: 13 | I69: 2026 | J69: 46235 | K69: 46280 | L69: 46 | M69: 2026 | N69: BRITOMJH | O69: 0424-9576055 | P69: LUIS ALFREDO VELÁSQUEZ ALCÁZAR | Q69: 17242954 | R69: DOCENTE MEDIA GENERAL
A70: 69 | B70: 18165536 | C70: BUSTAMANTE CASTILLO | D70: KATHERINE | E70: UE SANTA BÁRBARA | F70: 8059721 | G70: 44635 | H70: 4 | I70: 2026 | J70: 46235 | K70: 46280 | L70: 46 | M70: 2026 | O70: 0412-4374938 | P70: LUIS ALFREDO VELÁSQUEZ ALCÁZAR | Q70: 17242954 | R70: DOCENTE MEDIA GENERAL
A71: 70 | B71: 15322399 | C71: CENTENO GAMBOA | D71: INGRID LORENA | E71: UE SANTA BÁRBARA | F71: 2094303 | G71: 08/03/2006 | H71: 20 | I71: 2026 | J71: 46235 | K71: 46280 | L71: 46 | M71: 2026 | N71: CENTENOI | O71: 0424-9385817 | P71: LUIS ALFREDO VELÁSQUEZ ALCÁZAR | Q71: 17242954 | R71: DOCENTE EDUCACIÓN INICIAL
A72: 71 | B72: 16808608 | C72: CHAVIEL RONDON | D72: ELIKA D | E72: UE SANTA BÁRBARA | F72: 2137969 | G72: 01/04/2009 | H72: 17 | I72: 2026 | J72: 46235 | K72: 46280 | L72: 46 | M72: 2026 | N72: CHAVIELE | O72: 0424-9319096 | P72: LUIS ALFREDO VELÁSQUEZ ALCÁZAR | Q72: 17242954 | R72: DIRECTOR ESCUELA SANTA BARBARA
A73: 72 | B73: 17240765 | C73: CLEMENTT BETANCOURT | D73: DELIZ VIOLETA | E73: UE SANTA BÁRBARA | F73: 8044827 | G73: 30/08/2019 | H73: 6 | I73: 2026 | J73: 46235 | K73: 46280 | L73: 46 | M73: 2026 | N73: CLEMENETTD | O73: 0412-0911478 | P73: LUIS ALFREDO VELÁSQUEZ ALCÁZAR | Q73: 17242954 | R73: DOCENTE MEDIA GENERAL
A74: 73 | B74: 14853914 | C74: CORDERO HERRERA | D74: ANA CELESTE | E74: UE SANTA BÁRBARA | F74: 8059706 | G74: 44008 | H74: 5 | I74: 2026 | J74: 46235 | K74: 46280 | L74: 46 | M74: 2026 | O74: 0414-8773757 | P74: LUIS ALFREDO VELÁSQUEZ ALCÁZAR | Q74: 17242954 | R74: DOCENTE EDUCACIÓN INICIAL
A75: 74 | B75: 19090864 | C75: DIAZ FEBRES | D75: MARICARMEN | E75: UE SANTA BÁRBARA | F75: 8059718 | G75: 44635 | H75: 4 | I75: 2026 | J75: 46235 | K75: 46280 | L75: 46 | M75: 2026 | O75: 0412-9284104 | P75: LUIS ALFREDO VELÁSQUEZ ALCÁZAR | Q75: 17242954 | R75: DOCENTE PRIMARIA
A76: 75 | B76: 18274614 | C76: DIAZ PACEDO | D76: YELITZA CAROLINA | E76: UE SANTA BÁRBARA | F76: 2177718 | G76: 09/04/2012 | H76: 14 | I76: 2026 | J76: 46235 | K76: 46280 | L76: 46 | M76: 2026 | N76: DIAZYCH | O76: 0424-9206962 | P76: LUIS ALFREDO VELÁSQUEZ ALCÁZAR | Q76: 17242954 | R76: COORDINADOR DE EVALUACIÓN
A77: 76 | B77: 15030333 | C77: FEBRES DE LOPEZ | D77: EUDIS TERESA | E77: UE SANTA BÁRBARA | F77: 8059716 | G77: 44635 | H77: 4 | I77: 2026 | J77: 46235 | K77: 46280 | L77: 46 | M77: 2026 | O77: 0424-9036845 | P77: LUIS ALFREDO VELÁSQUEZ ALCÁZAR | Q77: 17242954 | R77: SUBDIRECTOR ACADÉMICO
A78: 77 | B78: 17090342 | C78: FERNANDEZ GUZMAN | D78: IRVIMAR JOSEFINA | E78: UE SANTA BÁRBARA | F78: 8059705 | G78: 15/03/2023 | H78: 3 | I78: 2026 | J78: 46235 | K78: 46280 | L78: 46 | M78: 2026 | O78: 0424-9685213 | P78: LUIS ALFREDO VELÁSQUEZ ALCÁZAR | Q78: 17242954 | R78: DOCENTE EDUCACIÓN INICIAL
A79: 78 | B79: 16939474 | C79: FIGUEROA | D79: ANA DAMELIS | E79: UE SANTA BÁRBARA | F79: 2184714 | G79: 06/08/2012 | H79: 13 | I79: 2026 | J79: 46235 | K79: 46280 | L79: 46 | M79: 2026 | N79: FIGUEROAADU | O79: 0416-8854426 | P79: LUIS ALFREDO VELÁSQUEZ ALCÁZAR | Q79: 17242954 | R79: DOCENTE MEDIA GENERAL
A80: 79 | B80: 21348248 | C80: FUENTES BUTTO | D80: MAIRENNYS MARGARITA | E80: UE SANTA BÁRBARA | F80: 2233280 | G80: 08/12/2016 | H80: 9 | I80: 2026 | J80: 46235 | K80: 46280 | L80: 46 | M80: 2026 | N80: FUENTESMQ | O80: 0424-9105676 | P80: LUIS ALFREDO VELÁSQUEZ ALCÁZAR | Q80: 17242954 | R80: DOCENTE MEDIA GENERAL
A81: 80 | B81: 17042206 | C81: FUNES OLIVEROS | D81: DAYANA ALEXANDRA | E81: UE SANTA BÁRBARA | F81: 8059723 | G81: 15/03/2022 | H81: 4 | I81: 2026 | J81: 46235 | K81: 46280 | L81: 46 | M81: 2026 | N81: FUNESDA | O81: 0412-2961844 | P81: LUIS ALFREDO VELÁSQUEZ ALCÁZAR | Q81: 17242954 | R81: PSICÓLOGO
A82: 81 | B82: 18268936 | C82: GARCIA DE HURTADO | D82: QUISMARYS | E82: UE SANTA BÁRBARA | F82: 8050015 | G82: 44008 | H82: 5 | I82: 2026 | J82: 46235 | K82: 46280 | L82: 46 | M82: 2026 | O82: 0426-5946054 0424-9324818 | P82: LUIS ALFREDO VELÁSQUEZ ALCÁZAR | Q82: 17242954 | R82: DOCENTE MEDIA GENERAL
A83: 82 | B83: 14661452 | C83: GOMEZ GOMEZ | D83: YURIMAR DEL VALLE | E83: UE SANTA BÁRBARA | F83: 2233278 | G83: 08/12/2016 | H83: 9 | I83: 2026 | J83: 46235 | K83: 46280 | L83: 46 | M83: 2026 | N83: GOMEZYDL | O83: 0414-7953513 | P83: LUIS ALFREDO VELÁSQUEZ ALCÁZAR | Q83: 17242954 | R83: DOCENTE MEDIA GENERAL
A84: 83 | B84: 18463048 | C84: GUERRA DE GALBAN | D84: LOURDES ELENA | E84: UE SANTA BÁRBARA | F84: 8050018 | G84: 44008 | H84: 5 | I84: 2026 | J84: 46235 | K84: 46280 | L84: 46 | M84: 2026 | O84: 0424-9166517 | P84: LUIS ALFREDO VELÁSQUEZ ALCÁZAR | Q84: 17242954 | R84: DOCENTE PRIMARIA
A85: 84 | B85: 15117427 | C85: IDROGO PONCE | D85: JOSE MIGUEL | E85: UE SANTA BÁRBARA | F85: 8044808 | G85: 30/08/2019 | H85: 6 | I85: 2026 | J85: 46235 | K85: 46280 | L85: 46 | M85: 2026 | N85: IDROGOJM | O85: 0414-3856272 | P85: LUIS ALFREDO VELÁSQUEZ ALCÁZAR | Q85: 17242954 | R85: DOCENTE MEDIA GENERAL
A86: 85 | B86: 12288989 | C86: JAUREGUI RODRIGUEZ | D86: VASNY RAFAEL | E86: UE SANTA BÁRBARA | F86: 2094296 | G86: 08/03/2006 | H86: 20 | I86: 2026 | J86: 46235 | K86: 46280 | L86: 46 | M86: 2026 | N86: JAUREGUIV | O86: 0424-9298141 | P86: LUIS ALFREDO VELÁSQUEZ ALCÁZAR | Q86: 17242954 | R86: ANALISTA MAYOR DE ESCUELA
A87: 86 | B87: 18010857 | C87: LOPEZ JIMENEZ | D87: YESENIA MARGARITA | E87: UE SANTA BÁRBARA | F87: 8044813 | G87: 43707 | H87: 6 | I87: 2026 | J87: 46235 | K87: 46280 | L87: 46 | M87: 2026 | O87: 0424-9528651 | P87: LUIS ALFREDO VELÁSQUEZ ALCÁZAR | Q87: 17242954 | R87: DOCENTE MEDIA GENERAL
A88: 87 | B88: 18272669 | C88: LOPEZ ZABALA | D88: EMILSA VERUSKA | E88: UE SANTA BÁRBARA | F88: 8050004 | G88: 44008 | H88: 5 | I88: 2026 | J88: 46235 | K88: 46280 | L88: 46 | M88: 2026 | O88: 0426-5951953 | P88: LUIS ALFREDO VELÁSQUEZ ALCÁZAR | Q88: 17242954 | R88: DOCENTE EDUCACIÓN INICIAL
A89: 88 | B89: 14859770 | C89: MAITA INAGAS | D89: SORINEE DEL VALLE | E89: UE SANTA BÁRBARA | F89: 2233277 | G89: 08/12/2016 | H89: 9 | I89: 2026 | J89: 46235 | K89: 46280 | L89: 46 | M89: 2026 | N89: MAITASD | O89: 0412-9411792 | P89: LUIS ALFREDO VELÁSQUEZ ALCÁZAR | Q89: 17242954 | R89: DOCENTE PRIMARIA
A90: 89 | B90: 14339477 | C90: MALAVE | D90: DIANA V | E90: UE SANTA BÁRBARA | F90: 2137949 | G90: 01/04/2009 | H90: 17 | I90: 2026 | J90: 46235 | K90: 46280 | L90: 46 | M90: 2026 | N90: MALAVEDV | O90: 0414-7672386 | P90: LUIS ALFREDO VELÁSQUEZ ALCÁZAR | Q90: 17242954 | R90: DOCENTE MEDIA GENERAL
A91: 90 | B91: 12968674 | C91: MARCANO GOITTE | D91: KARINA DEL CARMEN | E91: UE SANTA BÁRBARA | F91: 8044801 | G91: 30/08/2019 | H91: 6 | I91: 2026 | J91: 46235 | K91: 46280 | L91: 46 | M91: 2026 | N91: MARCANOKB | O91: 0416-2987100 | P91: LUIS ALFREDO VELÁSQUEZ ALCÁZAR | Q91: 17242954 | R91: DOCENTE PRIMARIA
A92: 91 | B92: 14859468 | C92: MARCANO ORTA | D92: MARIA DEL VALLE | E92: UE SANTA BÁRBARA | F92: 2065537 | G92: 14/04/2003 | H92: 23 | I92: 2026 | J92: 46235 | K92: 46280 | L92: 46 | M92: 2026 | N92: MARCANOMW | O92: 0414-8977788 | P92: LUIS ALFREDO VELÁSQUEZ ALCÁZAR | Q92: 17242954 | R92: COORDINADOR PEDAGÓGICO
A93: 92 | B93: 17546889 | C93: MARTINEZ GUEVARA | D93: KARELIS DEL VALLE | E93: UE SANTA BÁRBARA | F93: 8045021 | G93: 16/10/2019 | H93: 6 | I93: 2026 | J93: 46235 | K93: 46280 | L93: 46 | M93: 2026 | N93: MARTINEZKF | O93: 0424-3735355 | P93: LUIS ALFREDO VELÁSQUEZ ALCÁZAR | Q93: 17242954 | R93: DOCENTE MEDIA GENERAL
A94: 93 | B94: 13476169 | C94: MARTINEZ JIMENEZ | D94: DAYVID DEL VALLE | E94: UE SANTA BÁRBARA | F94: 2124562 | G94: 31/03/2008 | H94: 18 | I94: 2026 | J94: 46235 | K94: 46280 | L94: 46 | M94: 2026 | N94: MARTINEZDDU | O94: 0412-4843781 | P94: LUIS ALFREDO VELÁSQUEZ ALCÁZAR | Q94: 17242954 | R94: DOCENTE MEDIA GENERAL
A95: 94 | B95: 15551039 | C95: MARTINEZ SALAZAR | D95: ARMANDO JOSE | E95: UE SANTA BÁRBARA | F95: 8059720 | G95: 44635 | H95: 4 | I95: 2026 | J95: 46235 | K95: 46280 | L95: 46 | M95: 2026 | O95: 0424-1710994 | P95: LUIS ALFREDO VELÁSQUEZ ALCÁZAR | Q95: 17242954 | R95: DOCENTE MEDIA GENERAL
A96: 95 | B96: 9896435 | C96: MEDINA BOLIVAR | D96: MARITZA COROMOTO | E96: UE SANTA BÁRBARA | F96: 2032689 | G96: 14/09/1998 | H96: 27 | I96: 2026 | J96: 46235 | K96: 46280 | L96: 46 | M96: 2026 | N96: MEDINAMMP | O96: 0414-3919204 | P96: LUIS ALFREDO VELÁSQUEZ ALCÁZAR | Q96: 17242954 | R96: ORIENTADOR
A97: 96 | B97: 21051939 | C97: NAVARRO CAMPOS | D97: JENNYFERTT ALEXANDRA | E97: UE SANTA BÁRBARA | F97: 8050016 | G97: 44008 | H97: 5 | I97: 2026 | J97: 46235 | K97: 46280 | L97: 46 | M97: 2026 | O97: 0414-0982824 | P97: LUIS ALFREDO VELÁSQUEZ ALCÁZAR | Q97: 17242954 | R97: PSICOPEDAGOGO
A98: 97 | B98: 17302888 | C98: NAVARRO GONZALEZ | D98: KARINA ANDREA | E98: UE SANTA BÁRBARA | F98: 8044803 | G98: 30/08/2019 | H98: 6 | I98: 2026 | J98: 46235 | K98: 46280 | L98: 46 | M98: 2026 | N98: NAVARROKA | O98: 0412-9455074 | P98: LUIS ALFREDO VELÁSQUEZ ALCÁZAR | Q98: 17242954 | R98: DOCENTE PRIMARIA
A99: 98 | B99: 14507966 | C99: PATETE MARCHAN | D99: ERIKA DEL VALLE | E99: UE SANTA BÁRBARA | F99: 2117173 | G99: 03/12/2007 | H99: 18 | I99: 2026 | J99: 46235 | K99: 46280 | L99: 46 | M99: 2026 | N99: PATETEE | O99: 0414-8783403 | P99: LUIS ALFREDO VELÁSQUEZ ALCÁZAR | Q99: 17242954 | R99: COORDINADOR PEDAGÓGICO
A100: 99 | B100: 16373334 | C100: PEREZ GARCIA | D100: NAIRETH CAROLINA | E100: UE SANTA BÁRBARA | F100: 8050012 | G100: 44008 | H100: 5 | I100: 2026 | J100: 46235 | K100: 46280 | L100: 46 | M100: 2026 | O100: 0424-9334127 | P100: LUIS ALFREDO VELÁSQUEZ ALCÁZAR | Q100: 17242954 | R100: DOCENTE MEDIA GENERAL
...

Sheet CONDICIONES
A3: TIPO DE PRESTAMO | C3: CONDICIÓN ACTUAL HABITABILIDAD
A4: INICIAL/ADQUISICIÓN | C4: 1) Habite en condición de hacinamiento, solo o con su grupo familiar.
A5: INICIAL/MEJORAS | C5: 2) Habite en condición de arrimado, solo o con su grupo familiar.
A6: ADICIONAL/ADQUISICIÓN | C6: 3) Habite en condición de alquiler, solo o con su grupo familiar.
A7: ADICIONAL/MEJORAS | C7: 4) Habite en condición de alquiler, con solicitud u orden de desalojo.
C8: 5) Habite en vivienda catalogada de alto riesgo, así declarado por la autoridad competente (Protección Civil o Bomberos)
C9: 6) Habite en vivienda prestada, bajo su cuidado.
A10: TRABAJADOR O FAMILIAR CON DISCAPACIDAD | C10: 7) Habite en un inmueble asignado, propiedad de la Empresa.
A11: SI | C11: 8) Habite un inmueble bajo otra condición diferente a las anteriores
A12: NO
A15: CÓNYUGE O CONCUBIN@ TRABAJADOR
A16: ES TRABAJADOR(A) ACTIVO(A)
A17: TRABAJÓ, ESTÁ RETIRADO
A18: NUNCA HA TRABAJO PDVSA
A21: ORDEN DE PRIORIDAD
A22: 1.) REQUIERE ATENCIÓN INMEDIATA/CASO CRÍTICO POR ALTO RIESGO Y/O ELEVADO NIVEL DE VULNERABILIDAD
A23: 2.) REQUIERE ATENCIÓN MEDIA (DEBE ATENDERSE DESPUÉS DE CASOS CRÍTICOS)
A24: 3.) REQUIERE ATENCIÓN NORMAL

Sheet GERENCIA 
A1: ESTRICTAMENTE CONFIDENCIAL
B2: Gerencia: | C2: Recursos Humanos
B3: Total FLE: | C3: 60
B4: Total trabajadores elegibles al PAAV: 47
B5: Total casos críticos:
A7: N | B7: CEDULA | C7: APELLIDOS Y NOMBRES | D7: GERENCIA | E7: PROCESO | F7: FECHA INGRESO | G7: ANTIGÜEDAD | H7: CARGA FAMILIAR SAP | I7: NUM HIJOS SAP | J7: CRITICIDAD | K7: TIPO DE PRÉSTAMO / MOTIVO DEL PRÉSTAMO | L7: ¿CUÁNTAS PERSONAS CONVIVEN EN EL NÚCLEO FAMILIAR DEL TRABAJADOR? | M7: ¿TRABAJADOR TIENE DISCAPACIDAD AVALADA POR EL CONAPDIS? | N7: OBSERVACIONES | O7: FAMILIAR CON DISCAPACIDAD AVALADA POR EL CONAPDIS? | P7: OBSERVACIONES | Q7: NOMBRE A APELLIDO DEL CÓNYUGE O CONCUBINA | R7: CÉDULA DE LA CÓNYUGE O CONCUBINA | S7: CÓNYUGE O CONCUBINA TRABAJA O TRABAJÓ EN PDVSA | T7: CONDICIÓN ACTUAL HABITABILIDAD | U7: OBSERVACIONES | V7: ORDEN DE PRIORIDAD | W7: se | AB7: 1
A8: 1 | B8: 17780095 | C8: JOSÉ VICENTE MILLÁN MONTAÑO | D8: RECURSOS HUMANOS | E8: ESCUELA | F8: =VLOOKUP(B8,Hoja2_2!$B$2:$G$110,6,0) -> 41127 | G8: =DATEDIF(F8,TODAY(),"y") -> 13 | K8: ADICIONAL/ADQUISICIÓN | L8: 3 | M8: NO | N8: SOLICITADO | O8: No | Q8: LORIANIS ZULLY CELIZ CASTILLO | R8: 17483709 | S8: ES TRABAJADOR(A) ACTIVO(A) | T8: 6) Habite en vivienda prestada, bajo su cuidado.
A9: 2 | B9: 18788707 | C9: YASIVIT DEL VALLE GONZÁLEZ GUISSEPPI | D9: RECURSOS HUMANOS | E9: ESCUELA | F9: =VLOOKUP(B9,Hoja2_2!$B$2:$G$110,6,0) -> 41008 | G9: =DATEDIF(F9,TODAY(),"y") -> 14 | K9: ADICIONAL/MEJORAS | L9: 3 | M9: NO | N9: SOLICITADO | O9: No | Q9: LUIS ALFREDO VELÁSQUEZ ALCAZAR | R9: 17242954 | S9: ES TRABAJADOR(A) ACTIVO(A) | T9: 8) Habite un inmueble bajo otra condición diferente a las anteriores
A10: 3 | B10: 14367610 | C10: ANA ELIUT GONZALEZ SALAZAR | D10: RECURSOS HUMANOS | E10: ESCUELA | F10: =VLOOKUP(B10,Hoja2_2!$B$2:$G$110,6,0) -> 38631 | G10: =DATEDIF(F10,TODAY(),"y") -> 20 | K10: ADICIONAL/MEJORAS | L10: 3 | M10: NO | N10: SOLICITADO | O10: No | Q10: DARWIN JOSÉ CORDERO GALLARDO | R10: 12538506 | S10: NUNCA HA TRABAJO PDVSA | T10: 8) Habite un inmueble bajo otra condición diferente a las anteriores
A11: 4 | B11: 14101477 | C11: MARYFRANCI ANYALI NORIEGA BARRETO | D11: RECURSOS HUMANOS | E11: ESCUELA | F11: =VLOOKUP(B11,Hoja2_2!$B$2:$G$110,6,0) -> 38412 | G11: =DATEDIF(F11,TODAY(),"y") -> 21 | K11: ADICIONAL/MEJORAS | L11: 3 | M11: NO | N11: SOLICITADO | O11: No | Q11: LUIS LORENZO VÉLIZ MOROCOIMA | R11: 11446707 | S11: NUNCA HA TRABAJO PDVSA | T11: 8) Habite un inmueble bajo otra condición diferente a las anteriores
A12: 5 | B12: 9286272 | C12: CARMEN ELENA RODRÍGUEZ PINTO | D12: RECURSOS HUMANOS | E12: ESCUELA | F12: =VLOOKUP(B12,Hoja2_2!$B$2:$G$110,6,0) -> 34613 | G12: =DATEDIF(F12,TODAY(),"y") -> 31 | K12: ADICIONAL/MEJORAS | L12: 2 | M12: NO | N12: PAGADO | O12: No | Q12: JUAN ANTONIO CERVANTES BROWN | R12: 84603455 | S12: NUNCA HA TRABAJO PDVSA | T12: 8) Habite un inmueble bajo otra condición diferente a las anteriores
A13: 6 | B13: 14110180 | C13: JUAN ENRIQUE ZAMBRANO RONDON | D13: RECURSOS HUMANOS | E13: ESCUELA | F13: =VLOOKUP(B13,Hoja2_2!$B$2:$G$110,6,0) -> 41008 | G13: =DATEDIF(F13,TODAY(),"y") -> 14 | K13: INICIAL/ADQUISICIÓN | L13: 2 | M13: NO | N13: PAGANDOLO | O13: No | Q13: NORKYS KARYNY HERNÁNDEZ MACHUCA | R13: 14703374 | S13: NUNCA HA TRABAJO PDVSA | T13: 8) Habite un inmueble bajo otra condición diferente a las anteriores
A14: 7 | B14: 14622890 | C14: ALBERTO RAFAEL MARTINEZ VILLAHERMOSA | D14: RECURSOS HUMANOS | E14: ESCUELA | F14: =VLOOKUP(B14,Hoja2_2!$B$2:$G$110,6,0) -> 43473 | G14: =DATEDIF(F14,TODAY(),"y") -> 7 | K14: INICIAL/ADQUISICIÓN | L14: 2 | M14: NO | N14: SOLICITADO | O14: No | Q14: YUSMERYS VALDIVIEZO | R14: 11006024 | S14: NUNCA HA TRABAJO PDVSA | T14: 2) Habite en condición de arrimado, solo o con su grupo familiar.
A15: 8 | B15: 13915005 | C15: BEATRÍZ JOSEFINA NUCCI CORTÉZ | D15: RECURSOS HUMANOS | E15: ESCUELA | F15: =VLOOKUP(B15,Hoja2_2!$B$2:$G$110,6,0) -> 37907 | G15: =DATEDIF(F15,TODAY(),"y") -> 22 | K15: ADICIONAL/MEJORAS | L15: 2 | M15: NO | N15: SOLICITADO | O15: No | T15: 8) Habite un inmueble bajo otra condición diferente a las anteriores
A16: 9 | B16: 22714341 | C16: DANIELA CAROLINA PERNIA HENRIQUEZ | D16: RECURSOS HUMANOS | E16: ESCUELA | F16: =VLOOKUP(B16,Hoja2_2!$B$2:$G$110,6,0) -> 43473 | G16: =DATEDIF(F16,TODAY(),"y") -> 7 | K16: INICIAL/ADQUISICIÓN | L16: 2 | M16: NO | N16: SOLICITADO | O16: No | T16: 1) Habite en condición de hacinamiento, solo o con su grupo familiar.
A17: 10 | B17: 12891949 | C17: DENYSSE JOSEFINA HERNANDEZ MACHADO | D17: RECURSOS HUMANOS | E17: ESCUELA | F17: =VLOOKUP(B17,Hoja2_2!$B$2:$G$110,6,0) -> 38621 | G17: =DATEDIF(F17,TODAY(),"y") -> 20 | K17: ADICIONAL/MEJORAS | L17: 3 | M17: NO | N17: SOLICITADO | O17: No | Q17: RAÚL ANTONIO RODRIGUEZ DEL NOGAL | R17: 9094695 | S17: NUNCA HA TRABAJO PDVSA | T17: 8) Habite un inmueble bajo otra condición diferente a las anteriores
A18: 11 | B18: 16375125 | C18: EIRA ALEJANDRA LEÓN PEÑA | D18: RECURSOS HUMANOS | E18: ESCUELA | F18: =VLOOKUP(B18,Hoja2_2!$B$2:$G$110,6,0) -> 39904 | G18: =DATEDIF(F18,TODAY(),"y") -> 17 | K18: ADICIONAL/MEJORAS | L18: 4 | M18: NO | N18: SOLICITADO | O18: No | Q18: CESAR VELASQUEZ ZABALA | R18: 15428693 | S18: ES TRABAJADOR(A) ACTIVO(A) | T18: 8) Habite un inmueble bajo otra condición diferente a las anteriores
A19: 12 | B19: 17546584 | C19: ELIANA LIZKEIRA GONZÁLEZ PLAZA | D19: RECURSOS HUMANOS | E19: ESCUELA | F19: =VLOOKUP(B19,Hoja2_2!$B$2:$G$110,6,0) -> 41008 | G19: =DATEDIF(F19,TODAY(),"y") -> 14 | K19: ADICIONAL/MEJORAS | L19: 4 | M19: NO | N19: SOLICITADO | O19: No | Q19: RANDY PEREZ | R19: 14111920 | S19: NUNCA HA TRABAJO PDVSA | T19: 8) Habite un inmueble bajo otra condición diferente a las anteriores
A20: 13 | B20: 16374774 | C20: ELINOR DEL VALLE HURTADO MARCANO | D20: RECURSOS HUMANOS | E20: ESCUELA | F20: =VLOOKUP(B20,Hoja2_2!$B$2:$G$110,6,0) -> 41754 | G20: =DATEDIF(F20,TODAY(),"y") -> 12 | K20: INICIAL/ADQUISICIÓN | L20: 1 | M20: NO | N20: PAGANDOLO | O20: No | T20: 8) Habite un inmueble bajo otra condición diferente a las anteriores
A21: 14 | B21: 16699098 | C21: FERNANDA ELISAMA LÓPEZ CARRASQUERO | D21: RECURSOS HUMANOS | E21: ESCUELA | F21: =VLOOKUP(B21,Hoja2_2!$B$2:$G$110,6,0) -> 43473 | G21: =DATEDIF(F21,TODAY(),"y") -> 7 | K21: INICIAL/ADQUISICIÓN | L21: 2 | M21: NO | N21: PAGANDOLO | O21: No | Q21: DANIEL ENRIQUE CEDEÑO ZAPATA | R21: 12792653 | S21: ES TRABAJADOR(A) ACTIVO(A) | T21: 8) Habite un inmueble bajo otra condición diferente a las anteriores
A22: 15 | B22: 16397151 | C22: FERNANDO DANIEL SALAZAR GONZÁLEZ | D22: RECURSOS HUMANOS | E22: ESCUELA | F22: =VLOOKUP(B22,Hoja2_2!$B$2:$G$110,6,0) -> 41127 | G22: =DATEDIF(F22,TODAY(),"y") -> 13 | K22: ADICIONAL/MEJORAS | L22: 2 | M22: NO | N22: SOLICITADO | O22: No | Q22: CRISTINA DEL CARMEN PIAMO CALZADILLA | R22: 15336800 | S22: TRABAJÓ, ESTÁ RETIRADO | T22: 8) Habite un inmueble bajo otra condición diferente a las anteriores
A23: 16 | B23: 18172869 | C23: ISABEL MARÍA ALBORNOZ MARCANO | D23: RECURSOS HUMANOS | E23: ESCUELA | F23: =VLOOKUP(B23,Hoja2_2!$B$2:$G$110,6,0) -> 43473 | G23: =DATEDIF(F23,TODAY(),"y") -> 7 | K23: INICIAL/MEJORAS | L23: 3 | M23: NO | N23: SOLICITADO | O23: No | Q23: LUIS ALEJANDRO GUEVARA CABELLO | R23: 11449043 | S23: TRABAJÓ, ESTÁ RETIRADO | T23: 8) Habite un inmueble bajo otra condición diferente a las anteriores
A24: 17 | B24: 19038253 | C24: ISLENY ADRIANA FUENMAYOR LIPORACHI | D24: RECURSOS HUMANOS | E24: ESCUELA | F24: =VLOOKUP(B24,Hoja2_2!$B$2:$G$110,6,0) -> 41754 | G24: =DATEDIF(F24,TODAY(),"y") -> 12 | K24: INICIAL/ADQUISICIÓN | L24: 1 | M24: NO | N24: PAGANDOLO | O24: No | T24: 8) Habite un inmueble bajo otra condición diferente a las anteriores
A25: 18 | B25: 17722878 | C25: JAMNYMAR JOSÉ JIMÉNEZ DE MÁRQUEZ | D25: RECURSOS HUMANOS | E25: ESCUELA | F25: =VLOOKUP(B25,Hoja2_2!$B$2:$G$110,6,0) -> 40470 | G25: =DATEDIF(F25,TODAY(),"y") -> 15 | K25: ADICIONAL/MEJORAS | L25: 4 | M25: NO | N25: SOLICITADO | O25: No | Q25: CARLOS GABRIEL MÁRQUEZ SALAZAR | R25: 17713009 | S25: NUNCA HA TRABAJO PDVSA | T25: 8) Habite un inmueble bajo otra condición diferente a las anteriores
A26: 19 | B26: 16722294 | C26: JESLHOR KATHERINE BRITO HERNÁNDEZ | D26: RECURSOS HUMANOS | E26: ESCUELA | F26: =VLOOKUP(B26,Hoja2_2!$B$2:$G$110,6,0) -> 41624 | G26: =DATEDIF(F26,TODAY(),"y") -> 12 | K26: INICIAL/ADQUISICIÓN | L26: 1 | M26: NO | N26: PAGANDOLO | O26: No | T26: 8) Habite un inmueble bajo otra condición diferente a las anteriores
A27: 20 | B27: 14703619 | C27: JOSÉ ÁNGEL LUCAS CARRASQUEL | D27: RECURSOS HUMANOS | E27: ESCUELA | F27: =VLOOKUP(B27,Hoja2_2!$B$2:$G$110,6,0) -> 41008 | G27: =DATEDIF(F27,TODAY(),"y") -> 14 | K27: INICIAL/MEJORAS | L27: 5 | M27: NO | N27: SOLICITADO | O27: No | Q27: MARÍA GABRIELA SMITH DE LUCAS | R27: 18652761 | S27: ES TRABAJADOR(A) ACTIVO(A) | T27: 8) Habite un inmueble bajo otra condición diferente a las anteriores
A28: 21 | B28: 14859067 | C28: JUAN CARLOS CANELÓN | D28: RECURSOS HUMANOS | E28: ESCUELA | F28: =VLOOKUP(B28,Hoja2_2!$B$2:$G$110,6,0) -> 43473 | G28: =DATEDIF(F28,TODAY(),"y") -> 7 | K28: INICIAL/MEJORAS | L28: 2 | M28: NO | N28: SOLICITADO | O28: No | Q28: MARIELLYS GONZALES | R28: 16710266 | S28: NUNCA HA TRABAJO PDVSA | T28: 8) Habite un inmueble bajo otra condición diferente a las anteriores
A29: 22 | B29: 20001991 | C29: JUAN CRICELIO GONZÁLEZ BARCELO | D29: RECURSOS HUMANOS | E29: ESCUELA | F29: =VLOOKUP(B29,Hoja2_2!$B$2:$G$110,6,0) -> 44596 | G29: =DATEDIF(F29,TODAY(),"y") -> 4 | K29: INICIAL/ADQUISICIÓN | L29: 2 | M29: NO | N29: SOLICITADO | O29: No | Q29: YELIS DEL CARMEN HERNANDEZ RODRIGUEZ | R29: 20002235 | S29: NUNCA HA TRABAJO PDVSA | T29: 2) Habite en condición de arrimado, solo o con su grupo familiar.
A30: 23 | B30: 19875121 | C30: JULIA ISABEL RUIZ VILLARROEL | D30: RECURSOS HUMANOS | E30: ESCUELA | F30: =VLOOKUP(B30,Hoja2_2!$B$2:$G$110,6,0) -> 41754 | G30: =DATEDIF(F30,TODAY(),"y") -> 12 | K30: ADICIONAL/MEJORAS | L30: 2 | M30: NO | N30: SOLICITADO | O30: No | Q30: EDUARDO JOSÉ VELASQUEZ RODRÍGUEZ | R30: 17782202 | S30: ES TRABAJADOR(A) ACTIVO(A) | T30: 8) Habite un inmueble bajo otra condición diferente a las anteriores
A31: 24 | B31: 13092755 | C31: KARINA DEL VALLE BARRETO SERRANO | D31: RECURSOS HUMANOS | E31: ESCUELA | F31: =VLOOKUP(B31,Hoja2_2!$B$2:$G$110,6,0) -> 38302 | G31: =DATEDIF(F31,TODAY(),"y") -> 21 | K31: ADICIONAL/ADQUISICIÓN | L31: 2 | M31: NO | N31: SOLICITADO | O31: No | T31: 2) Habite en condición de arrimado, solo o con su grupo familiar.
A32: 25 | B32: 13656273 | C32: LAURYS DEL VALLE MILLÁN DE RIVAS | D32: RECURSOS HUMANOS | E32: ESCUELA | F32: =VLOOKUP(B32,Hoja2_2!$B$2:$G$110,6,0) -> 39461 | G32: =DATEDIF(F32,TODAY(),"y") -> 18 | K32: INICIAL/ADQUISICIÓN | L32: 4 | M32: NO | N32: PAGANDOLO | O32: No | Q32: JESÚS AQUILES RIVAS HERNÁNDEZ | R32: 9899154 | S32: ES TRABAJADOR(A) ACTIVO(A) | T32: 8) Habite un inmueble bajo otra condición diferente a las anteriores
A33: 26 | B33: 17483709 | C33: LORIANIS ZULLYN CELIZ CASTILLO | D33: RECURSOS HUMANOS | E33: ESCUELA | F33: =VLOOKUP(B33,Hoja2_2!$B$2:$G$110,6,0) -> 41222 | G33: =DATEDIF(F33,TODAY(),"y") -> 13 | K33: ADICIONAL/ADQUISICIÓN | L33: 3 | M33: NO | N33: SOLICITADO | O33: No | Q33: JOSÉ VICENTE MILLAN MONTAÑO | R33: 17780095 | S33: ES TRABAJADOR(A) ACTIVO(A) | T33: 6) Habite en vivienda prestada, bajo su cuidado.
A34: 27 | B34: 19079457 | C34: LUIS JOSE RIVAS ROMERO | D34: RECURSOS HUMANOS | E34: ESCUELA | F34: =VLOOKUP(B34,Hoja2_2!$B$2:$G$110,6,0) -> 43473 | G34: =DATEDIF(F34,TODAY(),"y") -> 7 | K34: INICIAL/ADQUISICIÓN | L34: 3 | M34: NO | N34: SOLICITADO | O34: No | T34: 5) Habite en vivienda catalogada de alto riesgo, así declarado por la autoridad competente (Protección Civil o Bomberos)
A35: 28 | B35: 17723779 | C35: LUISA JOSÉ JIMÉNEZ NUÑEZ | D35: RECURSOS HUMANOS | E35: ESCUELA | F35: =VLOOKUP(B35,Hoja2_2!$B$2:$G$110,6,0) -> 43473 | G35: =DATEDIF(F35,TODAY(),"y") -> 7 | K35: INICIAL/ADQUISICIÓN | L35: 3 | M35: NO | N35: SOLICITADO | O35: No | Q35: MANRIQUE MANUEL ALEJANDRO | R35: 16691883 | S35: NUNCA HA TRABAJO PDVSA | T35: 6) Habite en vivienda prestada, bajo su cuidado.
A36: 29 | B36: 17463095 | C36: MARÍA JOSÉ MARTÍNEZ OLIVEROS | D36: RECURSOS HUMANOS | E36: ESCUELA | F36: =VLOOKUP(B36,Hoja2_2!$B$2:$G$110,6,0) -> 43473 | G36: =DATEDIF(F36,TODAY(),"y") -> 7 | K36: INICIAL/ADQUISICIÓN | L36: 1 | M36: NO | N36: SOLICITADO | O36: No | Q36: ALEJANDRO JOSÉ RODRÍGUEZ VILLARROEL | R36: 16926442 | S36: ES TRABAJADOR(A) ACTIVO(A) | T36: 6) Habite en vivienda prestada, bajo su cuidado.
A37: 30 | B37: 17241569 | C37: MARTÍN EDUARDO MARCANO | D37: RECURSOS HUMANOS | E37: ESCUELA | F37: =VLOOKUP(B37,Hoja2_2!$B$2:$G$110,6,0) -> 41754 | G37: =DATEDIF(F37,TODAY(),"y") -> 12 | K37: ADICIONAL/MEJORAS | L37: 3 | M37: NO | N37: SOLICITADO | O37: No | Q37: TERESA CORTEZ | R37: 16710908 | S37: NUNCA HA TRABAJO PDVSA | T37: 8) Habite un inmueble bajo otra condición diferente a las anteriores
A38: 31 | B38: 14531830 | C38: MINERVA JOSEFINA MARTIN GUZMAN | D38: RECURSOS HUMANOS | E38: ESCUELA | F38: =VLOOKUP(B38,Hoja2_2!$B$2:$G$110,6,0) -> 43108 | G38: =DATEDIF(F38,TODAY(),"y") -> 8 | K38: INICIAL/ADQUISICIÓN | L38: 2 | M38: NO | N38: SOLICITADO | O38: No | Q38: PEDRO RAMON TINEO PALMA | R38: 13544171 | S38: ES TRABAJADOR(A) ACTIVO(A) | T38: 8) Habite un inmueble bajo otra condición diferente a las anteriores
A39: 32 | B39: 12067865 | C39: NEIDA MARGARITA GARCIA DE ROJAS | D39: RECURSOS HUMANOS | E39: ESCUELA | F39: =VLOOKUP(B39,Hoja2_2!$B$2:$G$110,6,0) -> 41628 | G39: =DATEDIF(F39,TODAY(),"y") -> 12 | K39: INICIAL/ADQUISICIÓN | L39: 2 | M39: NO | N39: PAGANDOLO | O39: No | T39: 8) Habite un inmueble bajo otra condición diferente a las anteriores
A40: 33 | B40: 11830987 | C40: OLGA ALICIA PARRA SALAZAR | D40: RECURSOS HUMANOS | E40: ESCUELA | F40: =VLOOKUP(B40,Hoja2_2!$B$2:$G$110,6,0) -> 37151 | G40: =DATEDIF(F40,TODAY(),"y") -> 24 | K40: ADICIONAL/MEJORAS | L40: 3 | M40: NO | N40: PAGADO | O40: No | Q40: JORGE LUIS APONTE SOSA | R40: 13452820 | S40: NUNCA HA TRABAJO PDVSA | T40: 8) Habite un inmueble bajo otra condición diferente a las anteriores
A41: 34 | B41: 16174810 | C41: OMAR RAFAEL RIVAS VILLARROEL | D41: RECURSOS HUMANOS | E41: ESCUELA | F41: =VLOOKUP(B41,Hoja2_2!$B$2:$G$110,6,0) -> 43837 | G41: =DATEDIF(F41,TODAY(),"y") -> 6 | K41: INICIAL/ADQUISICIÓN | L41: 2 | M41: NO | N41: PAGANDOLO | O41: No | T41: 8) Habite un inmueble bajo otra condición diferente a las anteriores
A42: 35 | B42: 19080636 | C42: PATRICIA CAROLINA DIAZ MOLINA | D42: RECURSOS HUMANOS | E42: ESCUELA | F42: =VLOOKUP(B42,Hoja2_2!$B$2:$G$110,6,0) -> 41753 | G42: =DATEDIF(F42,TODAY(),"y") -> 12 | K42: INICIAL/ADQUISICIÓN | L42: 1 | M42: NO | N42: SOLICITADO | O42: No | T42: 3) Habite en condición de alquiler, solo o con su grupo familiar.
A43: 36 | B43: 19603449 | C43: PATRICIA DEL JESÚS ACOSTA DÍAZ | D43: RECURSOS HUMANOS | E43: ESCUELA | F43: =VLOOKUP(B43,Hoja2_2!$B$2:$G$110,6,0) -> 43473 | G43: =DATEDIF(F43,TODAY(),"y") -> 7 | K43: INICIAL/ADQUISICIÓN | L43: 3 | M43: NO | N43: SOLICITADO | O43: No | Q43: JUAN MANUEL MARTÍNEZ VILLANUEVA | R43: 14111509 | S43: NUNCA HA TRABAJO PDVSA | T43: 2) Habite en condición de arrimado, solo o con su grupo familiar.
A44: 37 | B44: 13814605 | C44: RUTHMARY JOSEFINA MORENO MARCANO | D44: RECURSOS HUMANOS | E44: ESCUELA | F44: =VLOOKUP(B44,Hoja2_2!$B$2:$G$110,6,0) -> 39993 | G44: =DATEDIF(F44,TODAY(),"y") -> 16 | K44: ADICIONAL/MEJORAS | L44: 2 | M44: NO | N44: SOLICITADO | O44: No | T44: 8) Habite un inmueble bajo otra condición diferente a las anteriores
A45: 38 | B45: 18274289 | C45: SULMARY MARÍA BEJAS | D45: RECURSOS HUMANOS | E45: ESCUELA | F45: =VLOOKUP(B45,Hoja2_2!$B$2:$G$110,6,0) -> 43473 | G45: =DATEDIF(F45,TODAY(),"y") -> 7 | K45: INICIAL/ADQUISICIÓN | L45: 4 | M45: NO | N45: SOLICITADO | O45: No | Q45: ORLANDO JOSÉ LEON FERMIN | R45: 18983095 | S45: NUNCA HA TRABAJO PDVSA | T45: 6) Habite en vivienda prestada, bajo su cuidado.
A46: 39 | B46: 16807474 | C46: TRINELLYS DELVALLE DURAN DE CARVAJAL | D46: RECURSOS HUMANOS | E46: ESCUELA | F46: =VLOOKUP(B46,Hoja2_2!$B$2:$G$110,6,0) -> 39904 | G46: =DATEDIF(F46,TODAY(),"y") -> 17 | K46: ADICIONAL/MEJORAS | L46: 2 | M46: NO | N46: SOLICITADO | O46: No | Q46: DICKSON CARVAJAL | R46: 17935775 | S46: NUNCA HA TRABAJO PDVSA | T46: 8) Habite un inmueble bajo otra condición diferente a las anteriores
A47: 40 | B47: 19415615 | C47: VANESSA DEL VALLE URRIETA ALEXANDER | D47: RECURSOS HUMANOS | E47: ESCUELA | F47: =VLOOKUP(B47,Hoja2_2!$B$2:$G$110,6,0) -> 43473 | G47: =DATEDIF(F47,TODAY(),"y") -> 7 | K47: INICIAL/ADQUISICIÓN | L47: 2 | M47: NO | N47: SOLICITADO | O47: No | Q47: PEDRO LUIS, LIMPIO ALFONZO | R47: 16938242 | S47: NUNCA HA TRABAJO PDVSA | T47: 5) Habite en vivienda catalogada de alto riesgo, así declarado por la autoridad competente (Protección Civil o Bomberos)
A48: 41 | B48: 18463516 | C48: VIRGINIA ADRUDIS AGUILERA | D48: RECURSOS HUMANOS | E48: ESCUELA | F48: =VLOOKUP(B48,Hoja2_2!$B$2:$G$110,6,0) -> 44214 | G48: =DATEDIF(F48,TODAY(),"y") -> 5 | K48: INICIAL/MEJORAS | L48: 4 | M48: NO | N48: SOLICITADO | O48: No | Q48: LUIS ALBERTO SÁNCHEZ BERMÚDEZ | R48: 14543609 | S48: ES TRABAJADOR(A) ACTIVO(A) | T48: 8) Habite un inmueble bajo otra condición diferente a las anteriores
A49: 42 | B49: 15044802 | C49: YADELSI CAROLINA PEINADO JIMÉNEZ | D49: RECURSOS HUMANOS | E49: ESCUELA | F49: =VLOOKUP(B49,Hoja2_2!$B$2:$G$110,6,0) -> 43473 | G49: =DATEDIF(F49,TODAY(),"y") -> 7 | K49: INICIAL/ADQUISICIÓN | L49: 2 | M49: NO | N49: PAGANDOLO | O49: No | T49: 8) Habite un inmueble bajo otra condición diferente a las anteriores
A50: 43 | B50: 17090701 | C50: YARITZA GABRIELA MAITA TORRES | D50: RECURSOS HUMANOS | E50: ESCUELA | F50: =VLOOKUP(B50,Hoja2_2!$B$2:$G$110,6,0) -> 39925 | G50: =DATEDIF(F50,TODAY(),"y") -> 17 | K50: ADICIONAL/MEJORAS | L50: 3 | M50: NO | N50: SOLICITADO | O50: No | Q50: JESUS FRANCISCO CLEMENTT BETANCOURT | R50: 14858541 | S50: ES TRABAJADOR(A) ACTIVO(A) | T50: 8) Habite un inmueble bajo otra condición diferente a las anteriores
A51: 44 | B51: 17933097 | C51: YENIRE ANDREINA GARCIA LAREZ | D51: RECURSOS HUMANOS | E51: ESCUELA | F51: =VLOOKUP(B51,Hoja2_2!$B$2:$G$110,6,0) -> 43473 | G51: =DATEDIF(F51,TODAY(),"y") -> 7 | K51: INICIAL/ADQUISICIÓN | L51: 2 | M51: NO | N51: PAGANDOLO | O51: No | T51: 8) Habite un inmueble bajo otra condición diferente a las anteriores
A52: 45 | B52: 19079220 | C52: BETZAIDA ZARAY GONZALEZ VARGAS | D52: RECURSOS HUMANOS | E52: ESCUELA | F52: =VLOOKUP(B52,Hoja2_2!$B$2:$G$110,6,0) -> 43707 | G52: =DATEDIF(F52,TODAY(),"y") -> 6 | K52: INICIAL/ADQUISICIÓN | L52: 2 | M52: NO | N52: PAGANDOLO | O52: No | T52: 8) Habite un inmueble bajo otra condición diferente a las anteriores
A53: 46 | B53: 15631248 | C53: YUDERCY ALEJANDRA MARCANO | D53: RECURSOS HUMANOS | E53: ESCUELA | F53: =VLOOKUP(B53,Hoja2_2!$B$2:$G$110,6,0) -> 43473 | G53: =DATEDIF(F53,TODAY(),"y") -> 7 | K53: INICIAL/ADQUISICIÓN | L53: 3 | M53: NO | N53: SOLICITADO | O53: No | T53: 1) Habite en condición de hacinamiento, solo o con su grupo familiar.
A54: 47 | B54: 17113644 | C54: MILAGROS DEL CARMEN MARTÍNEZ MALPICA | D54: RECURSOS HUMANOS | E54: ESCUELA | F54: =VLOOKUP(B54,Hoja2_2!$B$2:$G$110,6,0) -> 16/12/2013 | G54: =DATEDIF(F54,TODAY(),"y") -> 12 | K54: INICIAL/ADQUISICIÓN | L54: 1 | M54: NO | N54: SOLICITADO | O54: No | T54: 2) Habite en condición de arrimado, solo o con su grupo familiar.
A55: 48 | B55: 18983523 | C55: ADRIANA MARGARITA RODRIGUEZ LOPEZ | D55: RECURSOS HUMANOS | E55: ESCUELA | F55: =VLOOKUP(B55,Hoja2_2!$B$2:$G$110,6,0) -> 44942 | G55: =DATEDIF(F55,TODAY(),"y") -> 3 | K55: INICIAL/ADQUISICIÓN | L55: 1 | M55: NO | N55: SOLICITADO | O55: No | Q55: EDWIN CHIRINOS | R55: 16374823 | S55: NUNCA HA TRABAJO PDVSA | T55: 6) Habite en vivienda prestada, bajo su cuidado.
A56: 49 | B56: 18174495 | C56: ROMINA DEL VALLE RUIZ | D56: RECURSOS HUMANOS | E56: ESCUELA | F56: =VLOOKUP(B56,Hoja2_2!$B$2:$G$110,6,0) -> 44942 | G56: =DATEDIF(F56,TODAY(),"y") -> 3 | K56: INICIAL/MEJORAS | L56: 2 | M56: NO | N56: SOLICITADO | O56: No | T56: 8) Habite un inmueble bajo otra condición diferente a las anteriores
A57: 50 | B57: 18080019 | C57: NELLYS JOSEFINA LOPEZ TORRES | D57: RECURSOS HUMANOS | E57: ESCUELA | F57: =VLOOKUP(B57,Hoja2_2!$B$2:$G$110,6,0) -> 44942 | G57: =DATEDIF(F57,TODAY(),"y") -> 3 | K57: INICIAL/ADQUISICIÓN | L57: 1 | M57: NO | N57: SOLICITADO | O57: No | T57: 3) Habite en condición de alquiler, solo o con su grupo familiar.
A58: 51 | B58: 22718748 | C58: FRANCHESCA GREYSIREE BERMUDEZ GONZALEZ | D58: RECURSOS HUMANOS | E58: ESCUELA | F58: =VLOOKUP(B58,Hoja2_2!$B$2:$G$110,6,0) -> 44942 | G58: =DATEDIF(F58,TODAY(),"y") -> 3 | K58: INICIAL/ADQUISICIÓN | L58: 1 | M58: NO | N58: SOLICITADO | O58: No | Q58: PABLO DILFREDO BOLIVAR OROZCO | R58: 20001903 | S58: NUNCA HA TRABAJO PDVSA | T58: 3) Habite en condición de alquiler, solo o con su grupo familiar.
A59: 52 | B59: 22720162 | C59: NOHELY SORIBEL GONZALEZ TREJO | D59: RECURSOS HUMANOS | E59: ESCUELA | F59: =VLOOKUP(B59,Hoja2_2!$B$2:$G$110,6,0) -> 44942 | G59: =DATEDIF(F59,TODAY(),"y") -> 3 | K59: INICIAL/ADQUISICIÓN | L59: 1 | M59: NO | N59: SOLICITADO | O59: No | Q59: MANUEL JOSÉ FIGUEROA LEZAMA | R59: 19537194 | S59: NUNCA HA TRABAJO PDVSA | T59: 6) Habite en vivienda prestada, bajo su cuidado.
A60: 53 | B60: 22725746 | C60: YOHANDRI DEL CARMEN RONDON GARCIA | D60: RECURSOS HUMANOS | E60: ESCUELA | F60: =VLOOKUP(B60,Hoja2_2!$B$2:$G$110,6,0) -> 44942 | G60: =DATEDIF(F60,TODAY(),"y") -> 3 | K60: INICIAL/ADQUISICIÓN | L60: 2 | M60: NO | N60: SOLICITADO | O60: No | Q60: JOSÉ RAFAEL GONZÁLEZ IDROGO | R60: 24504332 | S60: NUNCA HA TRABAJO PDVSA | T60: 3) Habite en condición de alquiler, solo o con su grupo familiar.
A61: 54 | B61: 19080588 | C61: JOSE ALY JIMENEZ ANGULO | D61: RECURSOS HUMANOS | E61: ESCUELA | F61: =VLOOKUP(B61,Hoja2_2!$B$2:$G$110,6,0) -> 44942 | G61: =DATEDIF(F61,TODAY(),"y") -> 3 | K61: INICIAL/ADQUISICIÓN | L61: 4 | M61: NO | N61: SOLICITADO | O61: No | Q61: EYLLING KEYROVICK GONZÁLEZ YANEZ | R61: 18075785 | S61: ES TRABAJADOR(A) ACTIVO(A) | T61: 2) Habite en condición de arrimado, solo o con su grupo familiar.
A62: 55 | B62: 20310911 | C62: MARIA ALEJANDRA MARTINEZ CABRERA | D62: RECURSOS HUMANOS | E62: ESCUELA | F62: =VLOOKUP(B62,Hoja2_2!$B$2:$G$110,6,0) -> 44942 | G62: =DATEDIF(F62,TODAY(),"y") -> 3 | K62: INICIAL/ADQUISICIÓN | L62: 3 | M62: NO | N62: SOLICITADO | O62: No | T62: 3) Habite en condición de alquiler, solo o con su grupo familiar.
A63: 56 | B63: 18075785 | C63: EYLLING KEYROVICK GONZALEZ YANEZ | D63: RECURSOS HUMANOS | E63: ESCUELA | F63: =VLOOKUP(B63,Hoja2_2!$B$2:$G$110,6,0) -> 44942 | G63: =DATEDIF(F63,TODAY(),"y") -> 3 | K63: INICIAL/ADQUISICIÓN | L63: 3 | M63: NO | N63: SOLICITADO | O63: No | Q63: JOSÉ ALY JIMÉNEZ ANGULO | R63: 19080588 | S63: ES TRABAJADOR(A) ACTIVO(A) | T63: 2) Habite en condición de arrimado, solo o con su grupo familiar.
A64: 57 | B64: 17092720 | C64: MARINELLYS COROMOTO RONDON VILLARROEL | D64: RECURSOS HUMANOS | E64: ESCUELA | F64: =VLOOKUP(B64,Hoja2_2!$B$2:$G$110,6,0) -> 39387 | G64: =DATEDIF(F64,TODAY(),"y") -> 18 | K64: ADICIONAL/MEJORAS | L64: 4 | M64: NO | N64: SOLICITADO | O64: No | Q64: JORGE LUIS PÉREZ GUAINA | R64: 16722404 | S64: ES TRABAJADOR(A) ACTIVO(A) | T64: 8) Habite un inmueble bajo otra condición diferente a las anteriores
A65: 58 | B65: 15335432 | C65: TEOBALDO JOSÉ FIGUEROA GASCÓN | D65: RECURSOS HUMANOS | E65: ESCUELA | F65: =VLOOKUP(B65,Hoja2_2!$B$2:$G$110,6,0) -> 38412 | G65: =DATEDIF(F65,TODAY(),"y") -> 21 | K65: INICIAL/MEJORAS | L65: 2 | M65: NO | N65: SOLICITADO | O65: No | Q65: ISBELYS JOSÉ MARCANO BELLO | R65: 16723836 | S65: ES TRABAJADOR(A) ACTIVO(A) | T65: 8) Habite un inmueble bajo otra condición diferente a las anteriores
A66: 59 | B66: 11381867 | C66: LUIS RICARDO SALMERON PRESILLA | D66: RECURSOS HUMANOS | E66: ESCUELA | F66: =VLOOKUP(B66,Hoja2_2!$B$2:$G$110,6,0) -> 38784 | G66: =DATEDIF(F66,TODAY(),"y") -> 20 | K66: ADICIONAL/MEJORAS | L66: 5 | M66: NO | N66: SOLICITADO | O66: No | Q66: JOANNOLIS HERNÁNDEZ | R66: 10933408 | S66: NUNCA HA TRABAJO PDVSA | T66: 8) Habite un inmueble bajo otra condición diferente a las anteriores
A67: 60 | B67: 17242954 | C67: LUIS ALFREDO VELÁSQUEZ ALCÁZAR | D67: RECURSOS HUMANOS | E67: ESCUELA | F67: =VLOOKUP(B67,Hoja2_2!$B$2:$G$110,6,0) -> 07/04/2008 | G67: =DATEDIF(F67,TODAY(),"y") -> 18 | K67: ADICIONAL/MEJORAS | L67: 3 | M67: NO | N67: SOLICITADO | O67: No | Q67: YASIVIT DEL VALLE GONZÁLEZ GUISSEPPI | R67: 18788707 | S67: ES TRABAJADOR(A) ACTIVO(A) | T67: 8) Habite un inmueble bajo otra condición diferente a las anteriores
A71: 1 | K71: INICIAL/ADQUISICIÓN | M71: NO | O71: NO | T71: 3) Habite en condición de alquiler, solo o con su grupo familiar. | V71: 1.) REQUIERE ATENCIÓN INMEDIATA/CASO CRÍTICO POR ALTO RIESGO Y/O ELEVADO NIVEL DE VULNERABILIDAD
A72: 2 | K72: ADICIONAL/MEJORAS | M72: NO | O72: NO | T72: 8) Habite un inmueble bajo otra condición diferente a las anteriores | V72: 2.) REQUIERE ATENCIÓN MEDIA (DEBE ATENDERSE DESPUÉS DE CASOS CRÍTICOS)
A73: 3 | K73: ADICIONAL/MEJORAS | M73: NO | O73: NO | T73: 8) Habite un inmueble bajo otra condición diferente a las anteriores | V73: 2.) REQUIERE ATENCIÓN MEDIA (DEBE ATENDERSE DESPUÉS DE CASOS CRÍTICOS)
A74: 4 | K74: ADICIONAL/MEJORAS | M74: NO | O74: SI | T74: 8) Habite un inmueble bajo otra condición diferente a las anteriores | V74: 2.) REQUIERE ATENCIÓN MEDIA (DEBE ATENDERSE DESPUÉS DE CASOS CRÍTICOS)
A75: 5 | K75: ADICIONAL/MEJORAS | M75: NO | O75: NO | T75: 8) Habite un inmueble bajo otra condición diferente a las anteriores | V75: 2.) REQUIERE ATENCIÓN MEDIA (DEBE ATENDERSE DESPUÉS DE CASOS CRÍTICOS)
A76: 6 | K76: INICIAL/ADQUISICIÓN | M76: NO | O76: NO | T76: 6) Habite en vivienda prestada, bajo su cuidado. | V76: 2.) REQUIERE ATENCIÓN MEDIA (DEBE ATENDERSE DESPUÉS DE CASOS CRÍTICOS)
